launch_lever/__init__.py
launch_lever/launch_lever.py
launch_lever-1.0.0.dist-info/METADATA
launch_lever-1.0.0.dist-info/WHEEL
launch_lever-1.0.0.dist-info/top_level.txt
launch_lever-1.0.0.dist-info/RECORD
