Metadata-Version: 2.1
Name: launch-lever
Version: 1.0.0
Summary: Manage feature toggles(flags) quickly
